dh123/__init__.py
dh123/download_file.py
dh123-0.1.dist-info/LICENSE
dh123-0.1.dist-info/METADATA
dh123-0.1.dist-info/WHEEL
dh123-0.1.dist-info/entry_points.txt
dh123-0.1.dist-info/top_level.txt
dh123-0.1.dist-info/RECORD
