Metadata-Version: 2.1
Name: dh123
Version: 0.1
Summary: Download DH.Java from GitHub
Author: Rajesh
License: MIT
Requires-Python: >=3.6
License-File: LICENSE
